{
    "id": 1,
    "test_name": "Spring Quiz",
    "subject": "Spring Quiz (Basic Multiple Choice Questions for Java Developers)",
    "questions": [
        {
            "id": 1010,
            "content": "What is Spring?",
            "test_id": 1, 
            "questionTypeId": 1,
            "difficulty": 1,
            "points": 2,
            "answers": [
                {
                    "id": 1055,
                    "question_id": 1010,
                    "content": "Spring is basically Hibernate on steroids. ",
                    "is_correct": false
                },
                {
                    "id": 1056,
                    "question_id": 1010,
                    "content": "Spring is an application framework written in Java used for Inversion of Control through Dependency Injection to alleviate the complex nature of developing enterprise-grade applications.",
                    "is_correct": true
                },
                {
                    "id": 1057,
                    "question_id": 1010,
                    "content": "Spring is used to connect a database to a web application. ",
                    "is_correct": false
                },
                {
                    "id": 1058,
                    "question_id": 1010,
                    "content": "Spring automates the entire DevOps pipeline.",
                    "is_correct": false
                }
            ]

        },
        {
            "id": 1011,
            "content": "In Aspect Oriented Programming: ",
            "test_id": 1,
            "questionTypeId": 1,
            "difficulty": 1,
            "answers": [
                {
                    "id": 1055,
                    "question_id": 1010,
                    "content": "classes are used as the key component to drive creation of objects, which serve the purpose of representing concrete ideas or things with states and behaviors. ",
                    "is_correct": false
                },
                {
                    "id": 1057,
                    "question_id": 1010,
                    "content": "dependencies are injected into models. ",
                    "is_correct": false
                },
                {
                    "id": 1056,
                    "question_id": 1010,
                    "content": "the key components modularize particular transactional concerns which can present across multiple classes known as cross-cutting concerns.",
                    "is_correct": true
                },
                {
                    "id": 1058,
                    "question_id": 1010,
                    "content": "functions are objects that can serve as input to other functions.",
                    "is_correct": false
                }
            ],
            "points": 2
        },
        {
            "id": 1012,
            "content": "Which API does Spring need to use to modify the behavior of methods and classes at runtime?",
            "test_id": 1,
            "questionTypeId": 1,
            "difficulty": 1,
            "answers": [
                {
                    "id": 1055,
                    "question_id": 1010,
                    "content": "Fetch API",
                    "is_correct": false
                },
                {
                    "id": 1057,
                    "question_id": 1010,
                    "content": "RxJS API",
                    "is_correct": false
                },
                {
                    "id": 1056,
                    "question_id": 1010,
                    "content": "Reflection API",
                    "is_correct": true
                },
                {
                    "id": 1058,
                    "question_id": 1010,
                    "content": "Jackson API",
                    "is_correct": false
                }
            ],
            "points": 2
        },
        {
            "id": 1013,
            "content": "Which of the following is NOT an example of a cross-cutting concern:",
            "test_id":1,
            "questionTypeId": 1,
            "difficulty": 1,
            "answers": [
                {
                    "id": 1055,
                    "question_id": 1010,
                    "content": "Instance field - data member of an object ",
                    "is_correct": true
                },
                {
                    "id": 1057,
                    "question_id": 1010,
                    "content": "Database Access - security for a database",
                    "is_correct": false
                },
                {
                    "id": 1056,
                    "question_id": 1010,
                    "content": "Data Entities - transactions to take place",
                    "is_correct": false
                },
                {
                    "id": 1058,
                    "question_id": 1010,
                    "content": "Error Handling - handling checked and unchecked exceptions and errors",
                    "is_correct": false
                }
            ],
            "points": 2
        },
        {
            "id": 1014,
            "content": "Weaving is:",
            "test_id": 1,
            "questionTypeId": 1,
            "difficulty": 1,
            "answers": [
                {
                    "id": 1055,
                    "question_id": 1010,
                    "content": "the chaining of objects",
                    "is_correct": false
                },
                {
                    "id": 1057,
                    "question_id": 1010,
                    "content": "the process of linking aspects with other objects, such as beans, to create advised objects.",
                    "is_correct": false
                },
                {
                    "id": 1056,
                    "question_id": 1010,
                    "content": "a defintiion of which methods in our application advice ought to be injected into or around",
                    "is_correct": false
                },
                {
                    "id": 1058,
                    "question_id": 1010,
                    "content": "declaration of new interfaces and corresponding implementations in subclasses of any advised object such that they are all functionally woven together",
                    "is_correct": true
                }
            ],
            "points": 2
        },
        {
            "id": 1015,
            "content": "What is the common goal between Lombok and Spring? ",
            "test_id": 1,
            "questionTypeId": 1,
            "difficulty": 1, 
            "answers": [
                {
                    "id": 1055,
                    "question_id": 1010,
                    "content": "To reduce the amount of boilerplate code by autogenerating the required code elements at compiletime.",
                    "is_correct": true
                },
                {
                    "id": 1057,
                    "question_id": 1010,
                    "content": "To make the workflow of a DevOps team more efficient. ",
                    "is_correct": false
                },
                {
                    "id": 1056,
                    "question_id": 1010,
                    "content": "To abstract away the need to write connective code between a database and Java objects.",
                    "is_correct": false
                },
                {
                    "id": 1058,
                    "question_id": 1010,
                    "content": "To autogenerate the XML configuration file that configures servlets. ",
                    "is_correct": false
                }
            ],
            "points": 2
        },
        {
            "id": 1016,
            "content": "Which of the following is used as the front controller in the Spring Web MVC Framework?",
            "test_id": 1, 
            "questionTypeId": 1,
            "difficulty": 1,
            "answers": [
                {
                    "id": 1055,
                    "question_id": 1010,
                    "content": "HttpServlet",
                    "is_correct": false
                },
                {
                    "id": 1056,
                    "question_id": 1010,
                    "content": " HelperServlet",
                    "is_correct": false
                },
                {
                    "id": 1057,
                    "question_id": 1010,
                    "content": "DispatcherServlet",
                    "is_correct": true
                },
                {
                    "id": 1058,
                    "question_id": 1010,
                    "content": "FrontControllerServlet",
                    "is_correct": false
                }
            ],
            "points": 2
        },
        {
            "id": 1017,
            "content": "Which of the following is not an endpoint for a Spring Boot Actuator?",
            "test_id": 1, 
            "questionTypeId": 1,
            "difficulty": 1,
            "answers": [
                {
                    "id": 1055,
                    "question_id": 1010,
                    "content": "/health",
                    "is_correct": false
                },
                {
                    "id": 1056,
                    "question_id": 1010,
                    "content": "/logfile",
                    "is_correct": false
                },
                {
                    "id": 1057,
                    "question_id": 1010,
                    "content": "/wiring",
                    "is_correct": true
                },
                {
                    "id": 1058,
                    "question_id": 1010,
                    "content": "/shutdown",
                    "is_correct": false
                }
            ],
            "points": 2
        },
        {
            "id": 1018,
            "content": "In Spring, RestTemplate acts as a: ",
            "test_id": 1,
            "questionTypeId": 1,
            "difficulty": 1,
            "answers": [
                {
                    "id": 1055,
                    "question_id": 1010,
                    "content": "web client to make requests to web services.",
                    "is_correct": true
                },
                {
                    "id": 1057,
                    "question_id": 1010,
                    "content": "a front controller to direct HTTP requests to their respective controllers.",
                    "is_correct": false
                },
                {
                    "id": 1056,
                    "question_id": 1010,
                    "content": "an aspect that controls the cross-cutting concern of security. ",
                    "is_correct": false
                },
                {
                    "id": 1058,
                    "question_id": 1010,
                    "content": "an interface that facilitates the conversion of JSON to Java objects",
                    "is_correct": false
                }
            ],
            "points": 2
        },
        {
            "id": 1019,
            "content": "Which of the following are the two major tools use to improve development workflow in Spring Boot applications?",
            "test_id": 1,
            "questionTypeId": 1,
            "difficulty": 1,
            "answers": [
                {
                    "id": 1055,
                    "question_id": 1010,
                    "content": "Hibernate and Jackson",
                    "is_correct": false
                },
                {
                    "id": 1056,
                    "question_id": 1010,
                    "content": "Disabling caching and manual restarts",
                    "is_correct": false
                },
                {
                    "id": 1057,
                    "question_id": 1010,
                    "content": "Jenkings and Docker",
                    "is_correct": false
                },
                {
                    "id": 1058,
                    "question_id": 1010,
                    "content": "Disabling caching and automatic restarts",
                    "is_correct": true
                }
            ],
            "points": 2
        }
    ]
}